Metadata-Version: 1.1
Name: pygments-agentspeak
Version: 1.0
Summary: Pygments lexer for Jason/JaCaMo AgentSpeak.
Home-page: UNKNOWN
Author: UNKNOWN
Author-email: UNKNOWN
License: BSD
Keywords: pygments agentspeak jason jacamo lexer
Platform: UNKNOWN
Classifier: Environment :: Plugins
Classifier: Intended Audience :: Developers
Classifier: License :: OSI Approved :: BSD License
Classifier: Operating System :: OS Independent
Classifier: Programming Language :: Python
Classifier: Programming Language :: Python :: 3
Classifier: Topic :: Software Development :: Libraries :: Python Modules
